{
    "resource_key": "HEADER_PASSWORD_CHANGE_PLEASE_CHANGE_IN_GOOGLE_PAGE",
    "legacy_resource_pid": 1541,
    "base_group_key": "grp-005-common-lib",
    "additional_group_keys": [],
    "key_for_update": "PDHBw3DriXj2rUSC9I3QERIhyF7HPK49HE9SXX9czhII5sMJKD2KAzzqnBTVzFuJsJclcIqHLzPgniBHuOc8N90NPzgB1fjAb9EmzrlLnXRsu6EBK2asDa1J3ktPNRm7",
    "sort_group": "PASSWORD CHANGE",
    "key_name": "HEADER_PASSWORD_CHANGE_PLEASE_CHANGE_IN_GOOGLE_PAGE",
    "key_name_for_xcode": "",
    "uwp_target_property": "",
    "is_resource_fixed": false,
    "use_default_if_caption_is_blank": true,
    "captions": {
        "ja": {
            "legacy_caption_pid": 6946,
            "legacy_language_pid": 1,
            "text": "Googleのパスワード変更ページで変更下さい。",
            "auto_translated": ""
        },
        "en": {
            "legacy_caption_pid": 6947,
            "legacy_language_pid": 2,
            "text": "Please change in the password change page of Google.",
            "auto_translated": ""
        },
        "zh-CN": {
            "legacy_caption_pid": 6948,
            "legacy_language_pid": 3,
            "text": "请在谷歌的密码更改页面更改。",
            "auto_translated": ""
        },
        "ko": {
            "legacy_caption_pid": 6949,
            "legacy_language_pid": 4,
            "text": "Google의 암호 변경 페이지에서 변경하세요.",
            "auto_translated": ""
        },
        "es": {
            "legacy_caption_pid": 10522,
            "legacy_language_pid": 5,
            "text": "Por favor, cambie la página de cambio de contraseña de Google.",
            "auto_translated": ""
        },
        "pt": {
            "legacy_caption_pid": 10523,
            "legacy_language_pid": 6,
            "text": "Altere a página de mudança de senha do Google.",
            "auto_translated": ""
        },
        "zh-TW": {
            "legacy_caption_pid": 10524,
            "legacy_language_pid": 7,
            "text": "請在谷歌的密碼更改頁面更改。",
            "auto_translated": ""
        },
        "fr": {
            "legacy_caption_pid": 16301,
            "legacy_language_pid": 8,
            "text": "Veuillez modifier la page de changement de mot de passe de Google.",
            "auto_translated": ""
        },
        "hi": {
            "legacy_caption_pid": 16302,
            "legacy_language_pid": 9,
            "text": "कृपया  गूगल के पासवर्ड परिवर्तन पृष्ठ में बदलें",
            "auto_translated": ""
        },
        "ar": {
            "legacy_caption_pid": 29954,
            "legacy_language_pid": 10,
            "text": "الرجاء تغيير في صفحة تغيير كلمة المرور غوغل.",
            "auto_translated": "الرجاء تغيير في صفحة تغيير كلمة المرور غوغل."
        },
        "fa": {
            "legacy_caption_pid": 29955,
            "legacy_language_pid": 11,
            "text": "لطفا در صفحه تغییر رمز عبور گوگل را تغییر دهید.",
            "auto_translated": "لطفا در صفحه تغییر رمز عبور گوگل را تغییر دهید."
        },
        "de": {
            "legacy_caption_pid": 29956,
            "legacy_language_pid": 12,
            "text": "Bitte ändern Sie in der Google-Passwort ändern Seite.",
            "auto_translated": "Bitte ändern Sie in der Google-Passwort ändern Seite."
        },
        "ru": {
            "legacy_caption_pid": 29957,
            "legacy_language_pid": 13,
            "text": "Пожалуйста, измените на странице изменения пароля Google.",
            "auto_translated": "Пожалуйста, измените на странице изменения пароля Google."
        },
        "ms": {
            "legacy_caption_pid": 29958,
            "legacy_language_pid": 14,
            "text": "Sila tukar di halaman pertukaran kata laluan Google.",
            "auto_translated": "Sila tukar di halaman pertukaran kata laluan Google."
        },
        "ta": {
            "legacy_caption_pid": 29959,
            "legacy_language_pid": 15,
            "text": "Google இன் கடவுச்சொல் மாற்றம் பக்கம் மாற்றவும்.",
            "auto_translated": "Google இன் கடவுச்சொல் மாற்றம் பக்கம் மாற்றவும்."
        },
        "it": {
            "legacy_caption_pid": 29960,
            "legacy_language_pid": 16,
            "text": "Si prega di cambiare pagina di modifica password di Google.",
            "auto_translated": "Si prega di cambiare pagina di modifica password di Google."
        },
        "bn": {
            "legacy_caption_pid": 29961,
            "legacy_language_pid": 17,
            "text": "দয়া করে Google এর পাসওয়ার্ড পরিবর্তন পৃষ্ঠা থেকে পরিবর্তন করুন।",
            "auto_translated": "দয়া করে Google এর পাসওয়ার্ড পরিবর্তন পৃষ্ঠা থেকে পরিবর্তন করুন।"
        },
        "tr": {
            "legacy_caption_pid": 29962,
            "legacy_language_pid": 18,
            "text": "Google'ın şifre değiştirme sayfasında değiştirin.",
            "auto_translated": "Google'ın şifre değiştirme sayfasında değiştirin."
        },
        "vi": {
            "legacy_caption_pid": 29963,
            "legacy_language_pid": 19,
            "text": "Vui lòng thay đổi trong trang thay đổi mật khẩu của Google.",
            "auto_translated": "Vui lòng thay đổi trong trang thay đổi mật khẩu của Google."
        },
        "pl": {
            "legacy_caption_pid": 29964,
            "legacy_language_pid": 20,
            "text": "Proszę zmienić na stronie Google'a zmiany hasła.",
            "auto_translated": "Proszę zmienić na stronie Google'a zmiany hasła."
        },
        "jv": {
            "legacy_caption_pid": 29965,
            "legacy_language_pid": 21,
            "text": "Mangga ngganti ing kaca owah-owahan sandi Google.",
            "auto_translated": "Mangga ngganti ing kaca owah-owahan sandi Google."
        },
        "pa": {
            "legacy_caption_pid": 29966,
            "legacy_language_pid": 22,
            "text": "ਕਿਰਪਾ ਕਰਕੇ Google ਦੇ ਪਾਸਵਰਡ ਤਬਦੀਲੀ ਸਫ਼ੇ ਵਿੱਚ ਤਬਦੀਲ ਕਰ.",
            "auto_translated": "ਕਿਰਪਾ ਕਰਕੇ Google ਦੇ ਪਾਸਵਰਡ ਤਬਦੀਲੀ ਸਫ਼ੇ ਵਿੱਚ ਤਬਦੀਲ ਕਰ."
        },
        "th": {
            "legacy_caption_pid": 29967,
            "legacy_language_pid": 23,
            "text": "กรุณาเปลี่ยนหน้าเปลี่ยนรหัสผ่านของ Google",
            "auto_translated": "กรุณาเปลี่ยนหน้าเปลี่ยนรหัสผ่านของ Google"
        },
        "te": {
            "legacy_caption_pid": 36536,
            "legacy_language_pid": 24,
            "text": "Google యొక్క పాస్వర్డ్ను మార్పు పేజీ లో మార్చండి.",
            "auto_translated": "Google యొక్క పాస్వర్డ్ను మార్పు పేజీ లో మార్చండి."
        },
        "mr": {
            "legacy_caption_pid": 36537,
            "legacy_language_pid": 25,
            "text": "कृपया Google संकेतशब्द बदल पृष्ठ बदला.",
            "auto_translated": "कृपया Google संकेतशब्द बदल पृष्ठ बदला."
        },
        "ur": {
            "legacy_caption_pid": 36538,
            "legacy_language_pid": 26,
            "text": "Google کے پاس ورڈ تبدیل کریں صفحہ میں تبدیل کریں.",
            "auto_translated": "Google کے پاس ورڈ تبدیل کریں صفحہ میں تبدیل کریں."
        },
        "gu": {
            "legacy_caption_pid": 36539,
            "legacy_language_pid": 27,
            "text": "કૃપા કરીને Google પાસવર્ડ બદલો પાનામાં બદલો.",
            "auto_translated": "કૃપા કરીને Google પાસવર્ડ બદલો પાનામાં બદલો."
        },
        "uk": {
            "legacy_caption_pid": 36540,
            "legacy_language_pid": 28,
            "text": "Будь ласка, поміняйте на сторінці зміни пароля Google.",
            "auto_translated": "Будь ласка, поміняйте на сторінці зміни пароля Google."
        },
        "ml": {
            "legacy_caption_pid": 36541,
            "legacy_language_pid": 29,
            "text": "Google ന്റെ പാസ്വേഡ് മാറ്റം പേജിൽ മാറ്റുക.",
            "auto_translated": "Google ന്റെ പാസ്വേഡ് മാറ്റം പേജിൽ മാറ്റുക."
        },
        "kn": {
            "legacy_caption_pid": 36542,
            "legacy_language_pid": 30,
            "text": "Google ನ ಪಾಸ್ವರ್ಡ್ ಬದಲಾವಣೆ ಪುಟದಲ್ಲಿ ಬದಲಾಯಿಸಿ.",
            "auto_translated": "Google ನ ಪಾಸ್ವರ್ಡ್ ಬದಲಾವಣೆ ಪುಟದಲ್ಲಿ ಬದಲಾಯಿಸಿ."
        },
        "su": {
            "legacy_caption_pid": 36543,
            "legacy_language_pid": 31,
            "text": "Mangga ngarobah dina kaca robah sandi Google.",
            "auto_translated": "Mangga ngarobah dina kaca robah sandi Google."
        },
        "ku": {
            "legacy_caption_pid": 36544,
            "legacy_language_pid": 32,
            "text": "Ji kerema xwe li rûpelê biguherîne şîfreya Google guhertin.",
            "auto_translated": "Ji kerema xwe li rûpelê biguherîne şîfreya Google guhertin."
        },
        "ps": {
            "legacy_caption_pid": 36545,
            "legacy_language_pid": 33,
            "text": "لطفا د ګوګل د پټنوم د بدلون مخ کې بدلون راولي.",
            "auto_translated": "لطفا د ګوګل د پټنوم د بدلون مخ کې بدلون راولي."
        },
        "ro": {
            "legacy_caption_pid": 36546,
            "legacy_language_pid": 34,
            "text": "Vă rugăm să schimbați în pagina de la Google schimbare a parolei.",
            "auto_translated": "Vă rugăm să schimbați în pagina de la Google schimbare a parolei."
        },
        "id": {
            "legacy_caption_pid": 36547,
            "legacy_language_pid": 35,
            "text": "Silahkan ubah di laman perubahan sandi Google.",
            "auto_translated": "Silahkan ubah di laman perubahan sandi Google."
        },
        "sd": {
            "legacy_caption_pid": 36548,
            "legacy_language_pid": 36,
            "text": "مهرباني ڪري گوگل جي پاس ورڊ تبديل ڪري صفحي ۾ تبديل ڪري.",
            "auto_translated": "مهرباني ڪري گوگل جي پاس ورڊ تبديل ڪري صفحي ۾ تبديل ڪري."
        },
        "af": {
            "legacy_caption_pid": 36549,
            "legacy_language_pid": 37,
            "text": "Asseblief verander in Google se wagwoord verander bladsy.",
            "auto_translated": "Asseblief verander in Google se wagwoord verander bladsy."
        },
        "sw": {
            "legacy_caption_pid": 36550,
            "legacy_language_pid": 38,
            "text": "Tafadhali badilisha katika ukurasa wa kubadilisha nenosiri ya Google.",
            "auto_translated": "Tafadhali badilisha katika ukurasa wa kubadilisha nenosiri ya Google."
        },
        "lo": {
            "legacy_caption_pid": 36551,
            "legacy_language_pid": 39,
            "text": "ກະລຸນາມີການປ່ຽນແປງໃນຫນ້າການປ່ຽນແປງລະຫັດຜ່ານຂອງກູໂກ.",
            "auto_translated": "ກະລຸນາມີການປ່ຽນແປງໃນຫນ້າການປ່ຽນແປງລະຫັດຜ່ານຂອງກູໂກ."
        },
        "nl": {
            "legacy_caption_pid": 36552,
            "legacy_language_pid": 40,
            "text": "Gelieve te veranderen in Google's wijziging van het wachtwoord pagina.",
            "auto_translated": "Gelieve te veranderen in Google's wijziging van het wachtwoord pagina."
        },
        "tl": {
            "legacy_caption_pid": 36553,
            "legacy_language_pid": 41,
            "text": "Mangyaring baguhin sa pahinang palitan ang password ng Google.",
            "auto_translated": "Mangyaring baguhin sa pahinang palitan ang password ng Google."
        },
        "ne": {
            "legacy_caption_pid": 36554,
            "legacy_language_pid": 42,
            "text": "कृपया गुगलको पासवर्ड परिवर्तन पृष्ठमा परिवर्तन।",
            "auto_translated": "कृपया गुगलको पासवर्ड परिवर्तन पृष्ठमा परिवर्तन।"
        },
        "hu": {
            "legacy_caption_pid": 36555,
            "legacy_language_pid": 43,
            "text": "Kérjük, módosítsa a Google jelszómódosítása oldalon.",
            "auto_translated": "Kérjük, módosítsa a Google jelszómódosítása oldalon."
        },
        "cs": {
            "legacy_caption_pid": 36556,
            "legacy_language_pid": 44,
            "text": "Změňte na stránce pro změnu hesla Google.",
            "auto_translated": "Změňte na stránce pro změnu hesla Google."
        },
        "el": {
            "legacy_caption_pid": 36557,
            "legacy_language_pid": 45,
            "text": "Παρακαλείστε να αλλάξει σελίδα αλλαγή κωδικού πρόσβασης του Google.",
            "auto_translated": "Παρακαλείστε να αλλάξει σελίδα αλλαγή κωδικού πρόσβασης του Google."
        },
        "sv": {
            "legacy_caption_pid": 36558,
            "legacy_language_pid": 46,
            "text": "Ändra i Googles lösenordsändring sida.",
            "auto_translated": "Ändra i Googles lösenordsändring sida."
        },
        "kk": {
            "legacy_caption_pid": 36559,
            "legacy_language_pid": 47,
            "text": "Google-дың құпия сөз өзгерту бетінде өзгертуге сұраймыз.",
            "auto_translated": "Google-дың құпия сөз өзгерту бетінде өзгертуге сұраймыз."
        },
        "fi": {
            "legacy_caption_pid": 36560,
            "legacy_language_pid": 48,
            "text": "Muuta Googlen salasanan vaihto sivulla.",
            "auto_translated": "Muuta Googlen salasanan vaihto sivulla."
        },
        "da": {
            "legacy_caption_pid": 36561,
            "legacy_language_pid": 49,
            "text": "Skift i Googles side adgangskode forandring.",
            "auto_translated": "Skift i Googles side adgangskode forandring."
        },
        "he": {
            "legacy_caption_pid": 36562,
            "legacy_language_pid": 50,
            "text": "אנא שנה ב דף שינוי הסיסמה של Google.",
            "auto_translated": "אנא שנה ב דף שינוי הסיסמה של Google."
        },
        "no": {
            "legacy_caption_pid": 36563,
            "legacy_language_pid": 51,
            "text": "Vennligst endre på Googles passordendring siden.",
            "auto_translated": "Vennligst endre på Googles passordendring siden."
        }
    }
}
